[{"longitude":"10.60904","governorate":"سوسة","delegation":"سوسة الرياض","center":"م إبتدائية الأمل حي الرياض - العهد الجديد","latitude":"35.801162"},{"longitude":"10.607559","governorate":"سوسة","delegation":"سوسة الرياض","center":"م إبتدائية السلام حي الرياض - العهد الجديد","latitude":"35.8057"},{"longitude":"10.600957","governorate":"سوسة","delegation":"سوسة الرياض","center":"م إبتدائية الفتح حي الرياض","latitude":"35.799645"},{"longitude":"10.600597","governorate":"سوسة","delegation":"سوسة الرياض","center":"م إبتدائية النجاح حي الرياض - العهد الجديد","latitude":"35.802601"},{"longitude":"10.583236","governorate":"سوسة","delegation":"سوسة الرياض","center":"م إبتدائية الرياض الخامس - حي الرياض","latitude":"35.803074"},{"longitude":"10.576465","governorate":"سوسة","delegation":"سوسة الرياض","center":"م إبتدائية السعادة حي الزهور","latitude":"35.790685"},{"longitude":"10.583592","governorate":"سوسة","delegation":"سوسة الرياض","center":"م إبتدائية الهداية حي الزهور","latitude":"35.790044"},{"longitude":"10.588329","governorate":"سوسة","delegation":"سوسة الرياض","center":"م إبتدائية المستقبل حي الزهور","latitude":"35.791638"},{"longitude":"10.582455","governorate":"سوسة","delegation":"سوسة الرياض","center":"م إبتدائية بورقيبة حي الزهور","latitude":"35.788337"},{"longitude":"10.596655","governorate":"سوسة","delegation":"سوسة الرياض","center":"م إبتدائية طارق ابن زياد حي الرياض","latitude":"35.797015"},{"longitude":"10.594568","governorate":"سوسة","delegation":"سوسة الرياض","center":"م إبتدائية ابن شرف حي الرياض - العهد الجديد","latitude":"35.803608"},{"longitude":"10.601831","governorate":"سوسة","delegation":"سوسة الرياض","center":"م إعدادية حي الرياض*","latitude":"35.806306"},{"longitude":"10.403692","governorate":"سوسة","delegation":"سيدي الهاني","center":"م إبتدائية غبغوب سيدي الهاني - سيدي الهاني الجنوبي…","latitude":"35.692523"},{"longitude":"10.312034","governorate":"سوسة","delegation":"سيدي الهاني","center":"م إبتدائية سيدي الهاني - سيدي الهاني المركزية","latitude":"35.680663"},{"longitude":"10.318151","governorate":"سوسة","delegation":"سيدي الهاني","center":"م إعدادية بسيدي الهاني*","latitude":"35.683822"},{"longitude":"10.336693","governorate":"سوسة","delegation":"سيدي الهاني","center":"م إبتدائية أولاد علي بلهاني سيدي الهاني","latitude":"35.711372"},{"longitude":"10.342917","governorate":"سوسة","delegation":"سيدي الهاني","center":"م إبتدائية أولاد بوبكر سيدي الهاني - سيدي الهاني ا…","latitude":"35.668747"},{"longitude":"10.272965","governorate":"سوسة","delegation":"سيدي الهاني","center":"م إبتدائية المويسات سيدي الهاني - سيدي الهاني الغر…","latitude":"35.688594"},{"longitude":"10.245846","governorate":"سوسة","delegation":"سيدي الهاني","center":"م إبتدائية أولاد الحشين - سيدي الهاني الغربية","latitude":"35.718109"},{"longitude":"10.230732","governorate":"سوسة","delegation":"سيدي الهاني","center":"م إبتدائية أولاد الصغير سيدي الهاني - سيدي الهاني …","latitude":"35.70685"},{"longitude":"10.256515","governorate":"سوسة","delegation":"سيدي الهاني","center":"م إبتدائية الشراشير سيدي الهاني - كروسية الغربية","latitude":"35.747139"},{"longitude":"10.325376","governorate":"سوسة","delegation":"سيدي الهاني","center":"م إبتدائية كروسية الشرقية سيدي الهاني - كروسية الغ…","latitude":"35.785558"},{"longitude":"10.316551","governorate":"سوسة","delegation":"سيدي الهاني","center":"م إبتدائية كروسية سيدي الهاني - كروسية المركزية","latitude":"35.757778"},{"longitude":"10.355827","governorate":"سوسة","delegation":"سيدي الهاني","center":"م إبتدائية العزيب - كروسية المركزية","latitude":"35.741051"},{"longitude":"10.597496","governorate":"سوسة","delegation":"حمام سوسة","center":"معهد حمام سوسة*","latitude":"35.853887"},{"longitude":"10.591275","governorate":"سوسة","delegation":"حمام سوسة","center":"م إبتدائية 25جويلية حمام سوسة - المدينة","latitude":"35.856863"},{"longitude":"10.593588","governorate":"سوسة","delegation":"حمام سوسة","center":"م إبتدائية طريق تونس حمام سوسة - المدينة","latitude":"35.862572"},{"longitude":"10.591593","governorate":"سوسة","delegation":"حمام سوسة","center":"م إبتدائية بورقيبة حمام سوسة - المدينة","latitude":"35.86013"},{"longitude":"10.586453","governorate":"سوسة","delegation":"حمام سوسة","center":"م إبتدائية الغربي حمام سوسة - الغرابي","latitude":"35.857294"},{"longitude":"10.603721","governorate":"سوسة","delegation":"حمام سوسة","center":"م إبتدائية طريق الشاطئ حمام سوسة - بئر موسى","latitude":"35.863242"},{"longitude":"10.594783","governorate":"سوسة","delegation":"حمام سوسة","center":"م إبتدائية سيدي القنطاوي حمام سوسة","latitude":"35.88752"},{"longitude":"10.587777","governorate":"سوسة","delegation":"حمام سوسة","center":"م إبتدائية سهلول حمام سوسة","latitude":"35.840555"},{"longitude":"10.555099","governorate":"سوسة","delegation":"اكودة","center":"م إبتدائية شط مريم","latitude":"35.93808"},{"longitude":"10.532746","governorate":"سوسة","delegation":"اكودة","center":"م إبتدائية الفقاعية","latitude":"35.959825"},{"longitude":"10.568106","governorate":"سوسة","delegation":"اكودة","center":"م إبتدائية طنطانة أكودة","latitude":"35.922783"},{"longitude":"10.562299","governorate":"سوسة","delegation":"اكودة","center":"م إبتدائية علي الحطاب - أكودة الغربية","latitude":"35.872411"},{"longitude":"10.565409","governorate":"سوسة","delegation":"اكودة","center":"م إبتدائية حاتم أكودة - أكودة الغربية","latitude":"35.882213"},{"longitude":"10.569507","governorate":"سوسة","delegation":"اكودة","center":"م إعدادية شارع البيئة أكودة*","latitude":"35.886192"},{"longitude":"10.570588","governorate":"سوسة","delegation":"اكودة","center":"م إبتدائية حشاد أكودة - أكودة الشرقية","latitude":"35.86946"},{"longitude":"10.567534","governorate":"سوسة","delegation":"اكودة","center":"م إبتدائية بورقيبة أكودة - أكودة الغربية","latitude":"35.865892"},{"longitude":"10.567904","governorate":"سوسة","delegation":"اكودة","center":"م إبتدائية الراجحية أكودة - أكودة الشرقية","latitude":"35.866795"},{"longitude":"10.57664","governorate":"سوسة","delegation":"اكودة","center":"م إبتدائية وادي العروق أكودة - أكودة الشرقية","latitude":"35.874887"},{"longitude":"10.641792","governorate":"سوسة","delegation":"سوسة المدينة","center":"م إبتدائية ابن خلدون سوسة - علي البلهوان","latitude":"35.814052"},{"longitude":"10.638919","governorate":"سوسة","delegation":"سوسة المدينة","center":"م إبتدائية الباب الشمالي سوسة - المدينة","latitude":"35.828958"},{"longitude":"10.637758","governorate":"سوسة","delegation":"سوسة المدينة","center":"م إبتدائية التريكية سوسة - المدينة","latitude":"35.821559"},{"longitude":"10.614862","governorate":"سوسة","delegation":"سوسة المدينة","center":"م إبتدائية الخزامة الشرقيــة سوسة - المدينة","latitude":"35.846715"},{"longitude":"10.638218","governorate":"سوسة","delegation":"سوسة المدينة","center":"م إبتدائية العمارات الجنوبية سوسة - علي البلهوان","latitude":"35.817979"},{"longitude":"10.633369","governorate":"سوسة","delegation":"سوسة المدينة","center":"م إبتدائية العمارات الشمالية سوسة - المدينة","latitude":"35.835782"},{"longitude":"10.635587","governorate":"سوسة","delegation":"سوسة المدينة","center":"م إعدادية النموذجية الباب الشمالي سوسة*","latitude":"35.828443"},{"longitude":"10.637457","governorate":"سوسة","delegation":"سوسة المدينة","center":"معهد سوسة*","latitude":"35.829098"},{"longitude":"10.625192","governorate":"سوسة","delegation":"سوسة جوهرة","center":"م إبتدائية حي التعمير سوسة - الهادي شاكر","latitude":"35.812785"},{"longitude":"10.615731","governorate":"سوسة","delegation":"سوسة جوهرة","center":"م إبتدائية بوخيزر - الهادي شاكر","latitude":"35.809331"},{"longitude":"10.623403","governorate":"سوسة","delegation":"سوسة جوهرة","center":"م إبتدائية بوحسينة","latitude":"35.820282"},{"longitude":"10.623923","governorate":"سوسة","delegation":"سوسة جوهرة","center":"م إبتدائية نهج المنصف باي سوسة - محمد القروي","latitude":"35.833362"},{"longitude":"10.621721","governorate":"سوسة","delegation":"سوسة جوهرة","center":"م إبتدائية الصفايا سوسة - محمد القروي","latitude":"35.836104"},{"longitude":"10.594251","governorate":"سوسة","delegation":"سوسة جوهرة","center":"م إبتدائية الامتياز سهلول 1 - وادي بليبان","latitude":"35.833773"},{"longitude":"10.610054","governorate":"سوسة","delegation":"سوسة جوهرة","center":"م إبتدائية خزامة الغربية - وادي بليبان","latitude":"35.839816"},{"longitude":"10.588414","governorate":"سوسة","delegation":"سوسة جوهرة","center":"م إبتدائية الطموح سهلول - وادي بليبان","latitude":"35.840661"},{"longitude":"10.598233","governorate":"سوسة","delegation":"سوسة جوهرة","center":"م إبتدائية الأخلاق حمام سوسة - سهلول","latitude":"35.854163"},{"longitude":"10.595607","governorate":"سوسة","delegation":"سوسة جوهرة","center":"م إبتدائية الوفاء سهلول - وادي بليبان","latitude":"35.842722"},{"longitude":"10.61461","governorate":"سوسة","delegation":"سوسة جوهرة","center":"م إبتدائية وادي غنيم - حشاد","latitude":"35.829189"},{"longitude":"10.627921","governorate":"سوسة","delegation":"سوسة جوهرة","center":"م إبتدائية نهج الغزالي سوسة - الهادي شاكر","latitude":"35.821323"},{"longitude":"10.616529","governorate":"سوسة","delegation":"سوسة جوهرة","center":"م إبتدائية 14 جانفي بوحسينة سوسة","latitude":"35.818711"},{"longitude":"10.631353","governorate":"سوسة","delegation":"سوسة جوهرة","center":"م إبتدائية نهج الحكيم قرول سوسة - محمد القروي","latitude":"35.831379"},{"longitude":"10.622634","governorate":"سوسة","delegation":"سوسة جوهرة","center":"م إعدادية محمد العروي بسوسة*","latitude":"35.831289"},{"longitude":"10.635","governorate":"سوسة","delegation":"سوسة سيدي عبد الحميد","center":"م إبتدائية الكفيف - الطيب المهيري","latitude":"35.814023"},{"longitude":"10.652703","governorate":"سوسة","delegation":"سوسة سيدي عبد الحميد","center":"م إبتدائية 2 مارس قصيبة الشط","latitude":"35.800329"},{"longitude":"10.64239","governorate":"سوسة","delegation":"سوسة سيدي عبد الحميد","center":"م إبتدائية ابن سينا سوسة - إبن خلدون","latitude":"35.805763"},{"longitude":"10.635572","governorate":"سوسة","delegation":"سوسة سيدي عبد الحميد","center":"م إبتدائية اسد بن الفرات - الطيب المهيري","latitude":"35.814013"},{"longitude":"10.633253","governorate":"سوسة","delegation":"سوسة سيدي عبد الحميد","center":"م إبتدائية حي الشباب سوسة - الطيب المهيري","latitude":"35.805835"},{"longitude":"10.626346","governorate":"سوسة","delegation":"سوسة سيدي عبد الحميد","center":"م إبتدائية حي العوينة سوسة - الطيب المهيري","latitude":"35.808501"},{"longitude":"10.639034","governorate":"سوسة","delegation":"سوسة سيدي عبد الحميد","center":"م إبتدائية خير الدين - إبن خلدون","latitude":"35.803115"},{"longitude":"10.663024","governorate":"سوسة","delegation":"سوسة سيدي عبد الحميد","center":"م إبتدائية سيدي عبد الحميد سوسة","latitude":"35.798186"},{"longitude":"10.650038","governorate":"سوسة","delegation":"سوسة سيدي عبد الحميد","center":"م إبتدائية قصيبة الشط سوسة","latitude":"35.803926"},{"longitude":"10.632951","governorate":"سوسة","delegation":"سوسة سيدي عبد الحميد","center":"م إبتدائية كدية مالك سوسة - الطيب المهيري","latitude":"35.811459"},{"longitude":"10.653435","governorate":"سوسة","delegation":"سوسة سيدي عبد الحميد","center":"م إعدادية إبن عرفة سيدي عبد الحميد سوسة*","latitude":"35.805664"},{"longitude":"10.466598","governorate":"سوسة","delegation":"سيدي بوعلي","center":"م إبتدائية ابن خلدون سيدي بوعلي","latitude":"35.955784"},{"longitude":"10.478067","governorate":"سوسة","delegation":"سيدي بوعلي","center":"م إبتدائية الأنصاري سيدي بوعلي","latitude":"35.957507"},{"longitude":"10.442115","governorate":"سوسة","delegation":"سيدي بوعلي","center":"م إبتدائية السد الشمالي سيدي بوعلي - السد الجوفي (…","latitude":"35.961926"},{"longitude":"10.399799","governorate":"سوسة","delegation":"سيدي بوعلي","center":"م إبتدائية الشويشة سيدي بوعلي","latitude":"35.970055"},{"longitude":"10.393805","governorate":"سوسة","delegation":"سيدي بوعلي","center":"م إبتدائية الكنانة سيدي بوعلي - السد الجوفي ( السط…","latitude":"35.948642"},{"longitude":"10.440666","governorate":"سوسة","delegation":"سيدي بوعلي","center":"م إبتدائية سدّ أولاد علي سيدي بوعلي - السد القبلي","latitude":"35.945697"},{"longitude":"10.436432","governorate":"سوسة","delegation":"سيدي بوعلي","center":"م إبتدائية سلمون سيدي بوعلي - المهاذبة","latitude":"35.997218"},{"longitude":"10.379278","governorate":"سوسة","delegation":"سيدي بوعلي","center":"م إبتدائية منزل المحطة سيدي بوعلي","latitude":"36.011503"},{"longitude":"10.44732","governorate":"سوسة","delegation":"سيدي بوعلي","center":"م إبتدائية وريمة سيدي بوعلي","latitude":"35.921345"},{"longitude":"10.463127","governorate":"سوسة","delegation":"سيدي بوعلي","center":"م إعدادية أحمد العواني بسيدي بوعلي*","latitude":"35.961028"},{"longitude":"10.508772","governorate":"سوسة","delegation":"هرقلة","center":"م إبتدائية الحبيب الكامل هرقلة","latitude":"36.029325"},{"longitude":"10.401495","governorate":"سوسة","delegation":"هرقلة","center":"م إبتدائية السويح هرقلة","latitude":"36.030648"},{"longitude":"10.463508","governorate":"سوسة","delegation":"هرقلة","center":"م إبتدائية العريبات هرقلة","latitude":"36.021013"},{"longitude":"10.494244","governorate":"سوسة","delegation":"هرقلة","center":"م إعدادية بهرقلة*","latitude":"36.028484"},{"longitude":"10.550529","governorate":"سوسة","delegation":"القلعة الصغرى","center":"م إبتدائية ابن خلدون القلعة الصغرى - القلعة الصغرى…","latitude":"35.82355"},{"longitude":"10.560503","governorate":"سوسة","delegation":"القلعة الصغرى","center":"م إبتدائية البشرى القلعة الصغرى - القلعة الصغرى ال…","latitude":"35.824799"},{"longitude":"10.5579","governorate":"سوسة","delegation":"القلعة الصغرى","center":"م إبتدائية الحبيب القلعة الصغرى - القلعة الصغرى حش…","latitude":"35.8318"},{"longitude":"10.511663","governorate":"سوسة","delegation":"القلعة الصغرى","center":"م إبتدائية النقر القلعة الصغرى","latitude":"35.799602"},{"longitude":"10.561651","governorate":"سوسة","delegation":"القلعة الصغرى","center":"م إبتدائية بورقيبة القلعة الصغرى - القلعة الصغرى ا…","latitude":"35.824326"},{"longitude":"10.58456","governorate":"سوسة","delegation":"القلعة الصغرى","center":"م إبتدائية حي المنازه القلعة الصغرى - القلعة الصغر…","latitude":"35.832117"},{"longitude":"10.580236","governorate":"سوسة","delegation":"القلعة الصغرى","center":"م إبتدائية حي المنازه2 - القلعة الصغرى الشرقية","latitude":"35.832781"},{"longitude":"10.563368","governorate":"سوسة","delegation":"القلعة الصغرى","center":"م إبتدائية غرة جوان القلعة الصغرى - القلعة الصغرى …","latitude":"35.819615"},{"longitude":"10.462492","governorate":"سوسة","delegation":"القلعة الصغرى","center":"م إبتدائية وادي لاية القلعة الصغرى","latitude":"35.800412"},{"longitude":"10.557787","governorate":"سوسة","delegation":"القلعة الصغرى","center":"م إعدادية محمد الهادي العامري بالـقـلـعــة الـصـغـ…","latitude":"35.832285"},{"longitude":"10.633418","governorate":"سوسة","delegation":"الزاوية - القصيبة - الثريات","center":"م إبتدائية 14 جانفي قصيبة سوسة","latitude":"35.764713"},{"longitude":"10.629602","governorate":"سوسة","delegation":"الزاوية - القصيبة - الثريات","center":"م إبتدائية الإمتياز - زاوية سوسة","latitude":"35.780846"},{"longitude":"10.651523","governorate":"سوسة","delegation":"الزاوية - القصيبة - الثريات","center":"م إبتدائية الثريات","latitude":"35.75729"},{"longitude":"10.620872","governorate":"سوسة","delegation":"الزاوية - القصيبة - الثريات","center":"م إبتدائية الجمهورية زاوية سوسة","latitude":"35.790686"},{"longitude":"10.628189","governorate":"سوسة","delegation":"الزاوية - القصيبة - الثريات","center":"م إبتدائية العفة قصيبة سوسة","latitude":"35.7672"},{"longitude":"10.630691","governorate":"سوسة","delegation":"الزاوية - القصيبة - الثريات","center":"م إبتدائية العهد الجديد زاوية سوسة","latitude":"35.792369"},{"longitude":"10.624682","governorate":"سوسة","delegation":"الزاوية - القصيبة - الثريات","center":"م إبتدائية علي البلهوان قصيبة سوسة","latitude":"35.770553"},{"longitude":"10.625714","governorate":"سوسة","delegation":"الزاوية - القصيبة - الثريات","center":"م إعدادية بالزاوية والقصيبة والثريات*","latitude":"35.777135"},{"longitude":"10.179193","governorate":"سوسة","delegation":"كندار","center":"م إبتدائية البشاشمة كندار","latitude":"35.840404"},{"longitude":"10.237793","governorate":"سوسة","delegation":"كندار","center":"م إبتدائية البلالمة كندار","latitude":"35.931095"},{"longitude":"10.323768","governorate":"سوسة","delegation":"كندار","center":"م إبتدائية القماطة كندار - القماطة","latitude":"35.962019"},{"longitude":"10.294256","governorate":"سوسة","delegation":"كندار","center":"م إبتدائية أولاد العابد","latitude":"35.989106"},{"longitude":"10.314131","governorate":"سوسة","delegation":"كندار","center":"م إبتدائية أولاد عامر - كندار","latitude":"36.012497"},{"longitude":"10.19432","governorate":"سوسة","delegation":"كندار","center":"م إبتدائية بئر الجديد كندار","latitude":"35.861956"},{"longitude":"10.300804","governorate":"سوسة","delegation":"كندار","center":"م إبتدائية كندار","latitude":"35.934604"},{"longitude":"10.314783","governorate":"سوسة","delegation":"كندار","center":"م إعدادية بكندار*","latitude":"35.930013"},{"longitude":"10.45324","governorate":"سوسة","delegation":"بوفيشة","center":"م إبتدائية 2مارس بوفيشة","latitude":"36.29997"},{"longitude":"10.475328","governorate":"سوسة","delegation":"بوفيشة","center":"م إبتدائية ابن الجزار السلوم بوفيشة","latitude":"36.28313"},{"longitude":"10.499276","governorate":"سوسة","delegation":"بوفيشة","center":"م إبتدائية الشابي كلم / 70 بوفيشة - سيدي مطير","latitude":"36.326444"},{"longitude":"10.344334","governorate":"سوسة","delegation":"بوفيشة","center":"م إبتدائية الصفحة بوفيشة","latitude":"36.186476"},{"longitude":"10.418839","governorate":"سوسة","delegation":"بوفيشة","center":"م إبتدائية المثاليث بوفيشة","latitude":"36.191043"},{"longitude":"10.458341","governorate":"سوسة","delegation":"بوفيشة","center":"م إبتدائية حشاد بوفبشة","latitude":"36.300258"},{"longitude":"10.451973","governorate":"سوسة","delegation":"بوفيشة","center":"م إبتدائية حي الرياض - بوفيشة","latitude":"36.292663"},{"longitude":"10.40418","governorate":"سوسة","delegation":"بوفيشة","center":"م إبتدائية سيدي خليفة بوفيشة","latitude":"36.255552"},{"longitude":"10.44919","governorate":"سوسة","delegation":"بوفيشة","center":"م إبتدائية سيدي سعيد بوفيشة","latitude":"36.336999"},{"longitude":"10.47773","governorate":"سوسة","delegation":"بوفيشة","center":"م إبتدائية سيدي مطير بوفيشة","latitude":"36.358013"},{"longitude":"10.420683","governorate":"سوسة","delegation":"بوفيشة","center":"م إبتدائية عين الرحمة بوفيشة","latitude":"36.230519"},{"longitude":"10.41197","governorate":"سوسة","delegation":"بوفيشة","center":"م إبتدائية لندرية بوفيشة - سيدي خليفة","latitude":"36.283482"},{"longitude":"10.402077","governorate":"سوسة","delegation":"بوفيشة","center":"م إبتدائية وادي الخروب بوفيشة","latitude":"36.313038"},{"longitude":"10.457845","governorate":"سوسة","delegation":"بوفيشة","center":"م إعدادية ببـوفيـشـة*","latitude":"36.298706"},{"longitude":"10.41656","governorate":"سوسة","delegation":"النفيضة","center":"م إبتدائية الشقارنية النفيضة","latitude":"36.165841"},{"longitude":"10.217045","governorate":"سوسة","delegation":"النفيضة","center":"م إبتدائية الصمايدية أولاد بالليل - قريميت الغربية","latitude":"36.069687"},{"longitude":"10.230258","governorate":"سوسة","delegation":"النفيضة","center":"م إبتدائية العياش - هيشر","latitude":"36.136403"},{"longitude":"10.240614","governorate":"سوسة","delegation":"النفيضة","center":"م إبتدائية الغواليف النفيضة - هيشر","latitude":"36.102782"},{"longitude":"10.293105","governorate":"سوسة","delegation":"النفيضة","center":"م إبتدائية الغويلات النفيضة - مرابط حشاد","latitude":"36.046124"},{"longitude":"10.319005","governorate":"سوسة","delegation":"النفيضة","center":"م إبتدائية الفرادي النفيضة - الفرادة","latitude":"36.107341"},{"longitude":"10.248787","governorate":"سوسة","delegation":"النفيضة","center":"م إبتدائية المدافعي النفيضة - قريميت الغربية","latitude":"36.04182"},{"longitude":"10.380824","governorate":"سوسة","delegation":"النفيضة","center":"م إبتدائية الهادي شاكر النفيضة","latitude":"36.134114"},{"longitude":"10.259296","governorate":"سوسة","delegation":"النفيضة","center":"م إبتدائية أولاد تليل النفيضة - مرابط حشاد","latitude":"36.047236"},{"longitude":"10.348978","governorate":"سوسة","delegation":"النفيضة","center":"م إبتدائية أولاد عبد الله النفيضة","latitude":"36.147046"},{"longitude":"10.333728","governorate":"سوسة","delegation":"النفيضة","center":"م إبتدائية تكرونة النفيضة","latitude":"36.152044"},{"longitude":"10.373869","governorate":"سوسة","delegation":"النفيضة","center":"م إبتدائية حشاد النفيضة","latitude":"36.132121"},{"longitude":"10.225842","governorate":"سوسة","delegation":"النفيضة","center":"م إبتدائية سيدي سعيدان النفيضة - قريميت الغربية","latitude":"36.054925"},{"longitude":"10.251644","governorate":"سوسة","delegation":"النفيضة","center":"م إبتدائية عين قارصي النفيضة","latitude":"36.145425"},{"longitude":"10.277342","governorate":"سوسة","delegation":"النفيضة","center":"م إبتدائية عين مذاكر النفيضة","latitude":"36.201268"},{"longitude":"10.273352","governorate":"سوسة","delegation":"النفيضة","center":"م إبتدائية قريميت الشرقية النفيضة","latitude":"36.113643"},{"longitude":"10.254939","governorate":"سوسة","delegation":"النفيضة","center":"م إبتدائية قريميت الغربية النفيضة","latitude":"36.078913"},{"longitude":"10.285009","governorate":"سوسة","delegation":"النفيضة","center":"م إبتدائية مرابط حشاد النفيضة","latitude":"36.080478"},{"longitude":"10.322751","governorate":"سوسة","delegation":"النفيضة","center":"م إبتدائية منزل دار بلواعر النفيضة","latitude":"36.037022"},{"longitude":"10.295364","governorate":"سوسة","delegation":"النفيضة","center":"م إبتدائية منزل فاتح النفيضة","latitude":"36.135909"},{"longitude":"10.206802","governorate":"سوسة","delegation":"النفيضة","center":"م إبتدائية هيشر النفيضة","latitude":"36.136533"},{"longitude":"10.372827","governorate":"سوسة","delegation":"النفيضة","center":"م إعدادية طريق زغوان بالنفيضة*","latitude":"36.135698"},{"longitude":"10.541837","governorate":"سوسة","delegation":"القلعة الكبرى","center":"م إبتدائية 14 جانفي القلعة الكبرى - الجرابعة","latitude":"35.862184"},{"longitude":"10.530515","governorate":"سوسة","delegation":"القلعة الكبرى","center":"م إبتدائية 2مارس القلعة الكبرى - أولاد محمد","latitude":"35.86817"},{"longitude":"10.542631","governorate":"سوسة","delegation":"القلعة الكبرى","center":"م إبتدائية 9أفريل القلعة الكبرى - الجرابعة","latitude":"35.871294"},{"longitude":"10.532432","governorate":"سوسة","delegation":"القلعة الكبرى","center":"م إبتدائية ابن خلدون القلعة الكبرى - الزعارنة الغر…","latitude":"35.871817"},{"longitude":"10.534313","governorate":"سوسة","delegation":"القلعة الكبرى","center":"م إبتدائية ابن عيسى القلعة الكبرى - أولاد محمد","latitude":"35.86919"},{"longitude":"10.414421","governorate":"سوسة","delegation":"القلعة الكبرى","center":"م إبتدائية البورة القلعة الكبرى - بلعوم","latitude":"35.893135"},{"longitude":"10.545538","governorate":"سوسة","delegation":"القلعة الكبرى","center":"م إبتدائية الحي الجديد القلعة الكبرى - الجرابعة","latitude":"35.86761"},{"longitude":"10.541917","governorate":"سوسة","delegation":"القلعة الكبرى","center":"م إبتدائية الحي الشرقي القلعة الكبرى - الزعارنة ال…","latitude":"35.875957"},{"longitude":"10.525412","governorate":"سوسة","delegation":"القلعة الكبرى","center":"م إبتدائية الزيتونة - أولاد محمد","latitude":"35.868644"},{"longitude":"10.393728","governorate":"سوسة","delegation":"القلعة الكبرى","center":"م إبتدائية القبو القلعة الكبرى - بلعوم","latitude":"35.838778"},{"longitude":"10.346579","governorate":"سوسة","delegation":"القلعة الكبرى","center":"م إبتدائية الكرارية القلعة الكبرى - السد الغربي","latitude":"35.927152"},{"longitude":"10.403122","governorate":"سوسة","delegation":"القلعة الكبرى","center":"م إبتدائية أهل جميع القلعة الكبرى - السد الغربي","latitude":"35.917864"},{"longitude":"10.527289","governorate":"سوسة","delegation":"القلعة الكبرى","center":"م إبتدائية حشاد القلعة الكبرى - الزعارنة الغربية","latitude":"35.878461"},{"longitude":"10.533756","governorate":"سوسة","delegation":"القلعة الكبرى","center":"م إبتدائية حي النزهة القلعة الكبرى - الزعارنة الشر…","latitude":"35.889553"},{"longitude":"10.388054","governorate":"سوسة","delegation":"القلعة الكبرى","center":"م إبتدائية سد الشياب القلعة الكبرى - السد الغربي","latitude":"35.93314"},{"longitude":"10.538067","governorate":"سوسة","delegation":"القلعة الكبرى","center":"م إبتدائية غرة جوان القلعة الكبرى - الجرابعة","latitude":"35.86972"},{"longitude":"10.553344","governorate":"سوسة","delegation":"القلعة الكبرى","center":"معهد علي بورقيبة بالقلعة الكبرى*","latitude":"35.867021"},{"longitude":"10.572995","governorate":"سوسة","delegation":"مساكن","center":"م إبتدائية 2مارس مساكن - الجبليين","latitude":"35.728702"},{"longitude":"10.590973","governorate":"سوسة","delegation":"مساكن","center":"م إبتدائية الإمام الشافعي مساكن - النور","latitude":"35.728592"},{"longitude":"10.576002","governorate":"سوسة","delegation":"مساكن","center":"م إبتدائية البرجين مساكن","latitude":"35.667366"},{"longitude":"10.587772","governorate":"سوسة","delegation":"مساكن","center":"م إبتدائية الحي الجديد مساكن - التوارة الشمالية","latitude":"35.736362"},{"longitude":"10.573548","governorate":"سوسة","delegation":"مساكن","center":"م إبتدائية الحي الشمالي مساكن - الجبليين","latitude":"35.727125"},{"longitude":"10.519387","governorate":"سوسة","delegation":"مساكن","center":"م إبتدائية الفرادة الجديدة مساكن","latitude":"35.590545"},{"longitude":"10.518891","governorate":"سوسة","delegation":"مساكن","center":"م إبتدائية الفرادة مساكن","latitude":"35.55216"},{"longitude":"10.562827","governorate":"سوسة","delegation":"مساكن","center":"م إبتدائية الكعيبي -مساكن - الجبليين","latitude":"35.722699"},{"longitude":"10.508348","governorate":"سوسة","delegation":"مساكن","center":"م إبتدائية الكنائس مساكن","latitude":"35.6783"},{"longitude":"10.600079","governorate":"سوسة","delegation":"مساكن","center":"م إبتدائية المسعدين 2 - المسعدين","latitude":"35.767706"},{"longitude":"10.596976","governorate":"سوسة","delegation":"مساكن","center":"م إبتدائية المسعدين مساكن","latitude":"35.761069"},{"longitude":"10.54721","governorate":"سوسة","delegation":"مساكن","center":"م إبتدائية المور الدين مساكن - النور","latitude":"35.761185"},{"longitude":"10.587118","governorate":"سوسة","delegation":"مساكن","center":"م إبتدائية النجاح مساكن - التوارة الشمالية","latitude":"35.735122"},{"longitude":"10.575844","governorate":"سوسة","delegation":"مساكن","center":"م إبتدائية النهوض مساكن - الغربيين","latitude":"35.721702"},{"longitude":"10.592558","governorate":"سوسة","delegation":"مساكن","center":"م إبتدائية النور مساكن - النور","latitude":"35.732351"},{"longitude":"10.464635","governorate":"سوسة","delegation":"مساكن","center":"م إبتدائية بشير الجبلين","latitude":"35.741328"},{"longitude":"10.5798","governorate":"سوسة","delegation":"مساكن","center":"م إبتدائية بطحاء السوق - النجاجرة","latitude":"35.728483"},{"longitude":"10.568485","governorate":"سوسة","delegation":"مساكن","center":"م إبتدائية بني ربيعة مساكن","latitude":"35.672525"},{"longitude":"10.588004","governorate":"سوسة","delegation":"مساكن","center":"م إبتدائية بني كلثوم مساكن","latitude":"35.702103"},{"longitude":"10.578708","governorate":"سوسة","delegation":"مساكن","center":"م إبتدائية حي التحرير مساكن - الجديدين","latitude":"35.738218"},{"longitude":"10.564747","governorate":"سوسة","delegation":"مساكن","center":"م إبتدائية سيدي عبار مساكن - الجبليين","latitude":"35.732565"},{"longitude":"10.582937","governorate":"سوسة","delegation":"مساكن","center":"م إبتدائية نهج البريد مساكن - النجاجرة","latitude":"35.725897"},{"longitude":"10.583982","governorate":"سوسة","delegation":"مساكن","center":"م إبتدائية نهج المحطة مساكن - القبليين","latitude":"35.72586"},{"longitude":"10.507206","governorate":"سوسة","delegation":"مساكن","center":"م إبتدائية وادي لاية - المردين","latitude":"35.772318"},{"longitude":"10.586805","governorate":"سوسة","delegation":"مساكن","center":"معهد ابن سينا بمساكن*","latitude":"35.736584"},{"longitude":"10.571843","governorate":"سوسة","delegation":"مساكن","center":"م إعدادية 2مارس 1934 بمساكن*","latitude":"35.729199"}]